tealogger/__init__.py
tealogger/filter.py
tealogger/formatter.py
tealogger/handler.py
tealogger/tealogger.py
tealogger/configuration/default.json
tealogger/configuration/schema.json
tealogger/configuration/schema.yaml
tealogger-0.9.0.dist-info/LICENSE
tealogger-0.9.0.dist-info/METADATA
tealogger-0.9.0.dist-info/WHEEL
tealogger-0.9.0.dist-info/top_level.txt
tealogger-0.9.0.dist-info/RECORD
