Metadata-Version: 2.1
Name: tealogger
Version: 0.9.0
Summary: Tea Logger
Author: TeaFTI
License: MIT License
Project-URL: Homepage, https://github.com/TeaFTI/Python-TeaLogger
Project-URL: Bug Tracker, https://github.com/TeaFTI/Python-TeaLogger/issues
Keywords: tealogger
Classifier: Development Status :: 3 - Alpha
Classifier: Intended Audience :: Developers
Classifier: Topic :: Software Development :: Libraries
Classifier: License :: OSI Approved :: MIT License
Classifier: Programming Language :: Python :: 3
Classifier: Programming Language :: Python :: 3.10
Classifier: Programming Language :: Python :: 3.11
Classifier: Programming Language :: Python :: 3.12
Requires-Python: >=3.10
License-File: LICENSE
Requires-Dist: pytest
Provides-Extra: develop
Requires-Dist: build; extra == "develop"
Requires-Dist: pytest-cov; extra == "develop"
Requires-Dist: pytest; extra == "develop"
Requires-Dist: ruff; extra == "develop"
Requires-Dist: twine; extra == "develop"
Provides-Extra: test
Requires-Dist: pytest-cov; extra == "test"
Requires-Dist: pytest; extra == "test"
Requires-Dist: ruff; extra == "test"
